{
  "玩偶": {
    "https://wogg.xxooo.cf": [
      {
        "timestamp": "2025-10-07T00:00:37.282989",
        "status": "up",
        "latency": 0.83335,
        "is_best": false
      },
      {
        "timestamp": "2025-10-07T01:00:20.326689",
        "status": "up",
        "latency": 0.791922,
        "is_best": false
      },
      {
        "timestamp": "2025-10-07T02:00:20.228888",
        "status": "up",
        "latency": 0.822158,
        "is_best": false
      },
      {
        "timestamp": "2025-10-07T03:00:26.102001",
        "status": "up",
        "latency": 0.811795,
        "is_best": false
      },
      {
        "timestamp": "2025-10-07T04:00:35.656550",
        "status": "up",
        "latency": 0.804423,
        "is_best": false
      },
      {
        "timestamp": "2025-10-07T05:00:20.460522",
        "status": "up",
        "latency": 0.794183,
        "is_best": false
      },
      {
        "timestamp": "2025-10-07T06:00:20.402500",
        "status": "up",
        "latency": 0.801455,
        "is_best": false
      },
      {
        "timestamp": "2025-10-07T07:00:19.902679",
        "status": "up",
        "latency": 0.804399,
        "is_best": false
      },
      {
        "timestamp": "2025-10-07T08:00:20.228669",
        "status": "up",
        "latency": 0.818027,
        "is_best": false
      },
      {
        "timestamp": "2025-10-07T09:00:24.502149",
        "status": "up",
        "latency": 0.836547,
        "is_best": false
      },
      {
        "timestamp": "2025-10-07T10:00:19.972862",
        "status": "up",
        "latency": 0.791442,
        "is_best": false
      },
      {
        "timestamp": "2025-10-07T11:00:20.624846",
        "status": "up",
        "latency": 0.793863,
        "is_best": false
      },
      {
        "timestamp": "2025-10-07T12:00:22.571614",
        "status": "up",
        "latency": 0.794493,
        "is_best": false
      },
      {
        "timestamp": "2025-10-07T13:00:23.788412",
        "status": "up",
        "latency": 0.792588,
        "is_best": false
      },
      {
        "timestamp": "2025-10-07T14:00:23.823051",
        "status": "up",
        "latency": 0.794584,
        "is_best": false
      },
      {
        "timestamp": "2025-10-07T15:00:24.480258",
        "status": "up",
        "latency": 0.792107,
        "is_best": false
      },
      {
        "timestamp": "2025-10-07T16:00:26.349987",
        "status": "up",
        "latency": 0.790997,
        "is_best": false
      },
      {
        "timestamp": "2025-10-07T17:00:25.777166",
        "status": "up",
        "latency": 0.7858,
        "is_best": false
      },
      {
        "timestamp": "2025-10-07T18:00:29.650938",
        "status": "up",
        "latency": 0.809639,
        "is_best": false
      },
      {
        "timestamp": "2025-10-07T19:01:02.538674",
        "status": "down",
        "latency": null,
        "is_best": false,
        "error_detail": "超时"
      },
      {
        "timestamp": "2025-10-07T20:00:34.005990",
        "status": "up",
        "latency": 0.87557,
        "is_best": false
      },
      {
        "timestamp": "2025-10-07T21:00:35.158508",
        "status": "up",
        "latency": 1.179243,
        "is_best": false
      },
      {
        "timestamp": "2025-10-07T22:00:35.422729",
        "status": "up",
        "latency": 0.80194,
        "is_best": false
      },
      {
        "timestamp": "2025-10-08T00:00:23.886730",
        "status": "up",
        "latency": 0.851911,
        "is_best": false
      }
    ],
    "https://wogg.333232.xyz": [
      {
        "timestamp": "2025-10-07T00:00:37.282989",
        "status": "up",
        "latency": 0.728232,
        "is_best": false
      },
      {
        "timestamp": "2025-10-07T01:00:20.326689",
        "status": "up",
        "latency": 1.02002,
        "is_best": false
      },
      {
        "timestamp": "2025-10-07T02:00:20.228888",
        "status": "up",
        "latency": 0.466593,
        "is_best": true
      },
      {
        "timestamp": "2025-10-07T03:00:26.102001",
        "status": "up",
        "latency": 0.453433,
        "is_best": true
      },
      {
        "timestamp": "2025-10-07T04:00:35.656550",
        "status": "up",
        "latency": 0.471215,
        "is_best": true
      },
      {
        "timestamp": "2025-10-07T05:00:20.460522",
        "status": "up",
        "latency": 0.887449,
        "is_best": false
      },
      {
        "timestamp": "2025-10-07T06:00:20.402500",
        "status": "up",
        "latency": 0.451433,
        "is_best": false
      },
      {
        "timestamp": "2025-10-07T07:00:19.902679",
        "status": "up",
        "latency": 0.650821,
        "is_best": false
      },
      {
        "timestamp": "2025-10-07T08:00:20.228669",
        "status": "up",
        "latency": 0.461484,
        "is_best": true
      },
      {
        "timestamp": "2025-10-07T09:00:24.502149",
        "status": "up",
        "latency": 0.459736,
        "is_best": true
      },
      {
        "timestamp": "2025-10-07T10:00:19.972862",
        "status": "up",
        "latency": 0.453645,
        "is_best": false
      },
      {
        "timestamp": "2025-10-07T11:00:20.624846",
        "status": "up",
        "latency": 0.496794,
        "is_best": true
      },
      {
        "timestamp": "2025-10-07T12:00:22.571614",
        "status": "up",
        "latency": 0.847826,
        "is_best": false
      },
      {
        "timestamp": "2025-10-07T13:00:23.788412",
        "status": "up",
        "latency": 0.489237,
        "is_best": true
      },
      {
        "timestamp": "2025-10-07T14:00:23.823051",
        "status": "up",
        "latency": 0.532932,
        "is_best": false
      },
      {
        "timestamp": "2025-10-07T15:00:24.480258",
        "status": "up",
        "latency": 0.693831,
        "is_best": false
      },
      {
        "timestamp": "2025-10-07T16:00:26.349987",
        "status": "up",
        "latency": 0.433731,
        "is_best": true
      },
      {
        "timestamp": "2025-10-07T17:00:25.777166",
        "status": "up",
        "latency": 0.560652,
        "is_best": false
      },
      {
        "timestamp": "2025-10-07T18:00:29.650938",
        "status": "up",
        "latency": 0.501316,
        "is_best": true
      },
      {
        "timestamp": "2025-10-07T19:01:02.538674",
        "status": "up",
        "latency": 0.561398,
        "is_best": true
      },
      {
        "timestamp": "2025-10-07T20:00:34.005990",
        "status": "up",
        "latency": 0.547795,
        "is_best": true
      },
      {
        "timestamp": "2025-10-07T21:00:35.158508",
        "status": "up",
        "latency": 1.049222,
        "is_best": false
      },
      {
        "timestamp": "2025-10-07T22:00:35.422729",
        "status": "up",
        "latency": 1.240665,
        "is_best": false
      },
      {
        "timestamp": "2025-10-08T00:00:23.886730",
        "status": "up",
        "latency": 0.645266,
        "is_best": true
      }
    ],
    "https://www.wogg.one": [
      {
        "timestamp": "2025-10-07T00:00:37.282989",
        "status": "up",
        "latency": 0.5569,
        "is_best": true
      },
      {
        "timestamp": "2025-10-07T01:00:20.326689",
        "status": "up",
        "latency": 0.963668,
        "is_best": false
      },
      {
        "timestamp": "2025-10-07T02:00:20.228888",
        "status": "up",
        "latency": 0.512053,
        "is_best": false
      },
      {
        "timestamp": "2025-10-07T03:00:26.102001",
        "status": "up",
        "latency": 0.821429,
        "is_best": false
      },
      {
        "timestamp": "2025-10-07T04:00:35.656550",
        "status": "up",
        "latency": 1.300962,
        "is_best": false
      },
      {
        "timestamp": "2025-10-07T05:00:20.460522",
        "status": "up",
        "latency": 0.441834,
        "is_best": true
      },
      {
        "timestamp": "2025-10-07T06:00:20.402500",
        "status": "up",
        "latency": 0.436028,
        "is_best": true
      },
      {
        "timestamp": "2025-10-07T07:00:19.902679",
        "status": "up",
        "latency": 0.456141,
        "is_best": true
      },
      {
        "timestamp": "2025-10-07T08:00:20.228669",
        "status": "up",
        "latency": 0.866596,
        "is_best": false
      },
      {
        "timestamp": "2025-10-07T09:00:24.502149",
        "status": "up",
        "latency": 2.54845,
        "is_best": false
      },
      {
        "timestamp": "2025-10-07T10:00:19.972862",
        "status": "up",
        "latency": 0.437301,
        "is_best": true
      },
      {
        "timestamp": "2025-10-07T11:00:20.624846",
        "status": "up",
        "latency": 0.497621,
        "is_best": false
      },
      {
        "timestamp": "2025-10-07T12:00:22.571614",
        "status": "up",
        "latency": 0.563422,
        "is_best": true
      },
      {
        "timestamp": "2025-10-07T13:00:23.788412",
        "status": "up",
        "latency": 0.750373,
        "is_best": false
      },
      {
        "timestamp": "2025-10-07T14:00:23.823051",
        "status": "up",
        "latency": 0.515151,
        "is_best": true
      },
      {
        "timestamp": "2025-10-07T15:00:24.480258",
        "status": "up",
        "latency": 0.571125,
        "is_best": true
      },
      {
        "timestamp": "2025-10-07T16:00:26.349987",
        "status": "up",
        "latency": 0.444231,
        "is_best": false
      },
      {
        "timestamp": "2025-10-07T17:00:25.777166",
        "status": "up",
        "latency": 0.451009,
        "is_best": true
      },
      {
        "timestamp": "2025-10-07T18:00:29.650938",
        "status": "up",
        "latency": 0.510207,
        "is_best": false
      },
      {
        "timestamp": "2025-10-07T19:01:02.538674",
        "status": "up",
        "latency": 1.755986,
        "is_best": false
      },
      {
        "timestamp": "2025-10-07T20:00:34.005990",
        "status": "up",
        "latency": 0.835038,
        "is_best": false
      },
      {
        "timestamp": "2025-10-07T21:00:35.158508",
        "status": "up",
        "latency": 0.845231,
        "is_best": false
      },
      {
        "timestamp": "2025-10-07T22:00:35.422729",
        "status": "up",
        "latency": 0.789632,
        "is_best": false
      },
      {
        "timestamp": "2025-10-08T00:00:23.886730",
        "status": "up",
        "latency": 0.693739,
        "is_best": false
      }
    ],
    "https://www.wogg.lol": [
      {
        "timestamp": "2025-10-07T00:00:37.282989",
        "status": "up",
        "latency": 0.824294,
        "is_best": false
      },
      {
        "timestamp": "2025-10-07T01:00:20.326689",
        "status": "up",
        "latency": 0.64429,
        "is_best": true
      },
      {
        "timestamp": "2025-10-07T02:00:20.228888",
        "status": "up",
        "latency": 0.756916,
        "is_best": false
      },
      {
        "timestamp": "2025-10-07T03:00:26.102001",
        "status": "up",
        "latency": 0.955474,
        "is_best": false
      },
      {
        "timestamp": "2025-10-07T04:00:35.656550",
        "status": "up",
        "latency": 0.568484,
        "is_best": false
      },
      {
        "timestamp": "2025-10-07T05:00:20.460522",
        "status": "up",
        "latency": 0.566505,
        "is_best": false
      },
      {
        "timestamp": "2025-10-07T06:00:20.402500",
        "status": "up",
        "latency": 0.933521,
        "is_best": false
      },
      {
        "timestamp": "2025-10-07T07:00:19.902679",
        "status": "up",
        "latency": 0.558398,
        "is_best": false
      },
      {
        "timestamp": "2025-10-07T08:00:20.228669",
        "status": "up",
        "latency": 0.538849,
        "is_best": false
      },
      {
        "timestamp": "2025-10-07T09:00:24.502149",
        "status": "up",
        "latency": 0.529269,
        "is_best": false
      },
      {
        "timestamp": "2025-10-07T10:00:19.972862",
        "status": "up",
        "latency": 0.615069,
        "is_best": false
      },
      {
        "timestamp": "2025-10-07T11:00:20.624846",
        "status": "up",
        "latency": 0.544302,
        "is_best": false
      },
      {
        "timestamp": "2025-10-07T12:00:22.571614",
        "status": "up",
        "latency": 0.906426,
        "is_best": false
      },
      {
        "timestamp": "2025-10-07T13:00:23.788412",
        "status": "up",
        "latency": 0.511161,
        "is_best": false
      },
      {
        "timestamp": "2025-10-07T14:00:23.823051",
        "status": "up",
        "latency": 1.16878,
        "is_best": false
      },
      {
        "timestamp": "2025-10-07T15:00:24.480258",
        "status": "up",
        "latency": 0.762216,
        "is_best": false
      },
      {
        "timestamp": "2025-10-07T16:00:26.349987",
        "status": "up",
        "latency": 0.971256,
        "is_best": false
      },
      {
        "timestamp": "2025-10-07T17:00:25.777166",
        "status": "up",
        "latency": 0.551808,
        "is_best": false
      },
      {
        "timestamp": "2025-10-07T18:00:29.650938",
        "status": "up",
        "latency": 0.660354,
        "is_best": false
      },
      {
        "timestamp": "2025-10-07T19:01:02.538674",
        "status": "up",
        "latency": 1.666402,
        "is_best": false
      },
      {
        "timestamp": "2025-10-07T20:00:34.005990",
        "status": "up",
        "latency": 0.63421,
        "is_best": false
      },
      {
        "timestamp": "2025-10-07T21:00:35.158508",
        "status": "up",
        "latency": 0.755849,
        "is_best": true
      },
      {
        "timestamp": "2025-10-07T22:00:35.422729",
        "status": "up",
        "latency": 0.686296,
        "is_best": true
      },
      {
        "timestamp": "2025-10-08T00:00:23.886730",
        "status": "up",
        "latency": 0.697111,
        "is_best": false
      }
    ]
  },
  "木偶": {
    "https://666.666291.xyz": [
      {
        "timestamp": "2025-10-07T00:00:37.282989",
        "status": "up",
        "latency": 1.944801,
        "is_best": false
      },
      {
        "timestamp": "2025-10-07T01:00:20.326689",
        "status": "up",
        "latency": 0.381291,
        "is_best": false
      },
      {
        "timestamp": "2025-10-07T02:00:20.228888",
        "status": "up",
        "latency": 0.345129,
        "is_best": false
      },
      {
        "timestamp": "2025-10-07T03:00:26.102001",
        "status": "up",
        "latency": 0.369952,
        "is_best": false
      },
      {
        "timestamp": "2025-10-07T04:00:35.656550",
        "status": "up",
        "latency": 0.335873,
        "is_best": true
      },
      {
        "timestamp": "2025-10-07T05:00:20.460522",
        "status": "up",
        "latency": 0.34253,
        "is_best": false
      },
      {
        "timestamp": "2025-10-07T06:00:20.402500",
        "status": "up",
        "latency": 0.351372,
        "is_best": false
      },
      {
        "timestamp": "2025-10-07T07:00:19.902679",
        "status": "up",
        "latency": 0.379251,
        "is_best": false
      },
      {
        "timestamp": "2025-10-07T08:00:20.228669",
        "status": "up",
        "latency": 0.34009,
        "is_best": true
      },
      {
        "timestamp": "2025-10-07T09:00:24.502149",
        "status": "up",
        "latency": 0.320992,
        "is_best": false
      },
      {
        "timestamp": "2025-10-07T10:00:19.972862",
        "status": "up",
        "latency": 1.413131,
        "is_best": false
      },
      {
        "timestamp": "2025-10-07T11:00:20.624846",
        "status": "up",
        "latency": 1.856493,
        "is_best": false
      },
      {
        "timestamp": "2025-10-07T12:00:22.571614",
        "status": "up",
        "latency": 2.863552,
        "is_best": false
      },
      {
        "timestamp": "2025-10-07T13:00:23.788412",
        "status": "up",
        "latency": 3.565417,
        "is_best": false
      },
      {
        "timestamp": "2025-10-07T14:00:23.823051",
        "status": "up",
        "latency": 2.03108,
        "is_best": false
      },
      {
        "timestamp": "2025-10-07T15:00:24.480258",
        "status": "up",
        "latency": 1.731019,
        "is_best": false
      },
      {
        "timestamp": "2025-10-07T16:00:26.349987",
        "status": "up",
        "latency": 4.76184,
        "is_best": false
      },
      {
        "timestamp": "2025-10-07T17:00:25.777166",
        "status": "up",
        "latency": 5.297383,
        "is_best": false
      },
      {
        "timestamp": "2025-10-07T18:00:29.650938",
        "status": "up",
        "latency": 4.176142,
        "is_best": false
      },
      {
        "timestamp": "2025-10-07T19:01:02.538674",
        "status": "up",
        "latency": 1.966683,
        "is_best": true
      },
      {
        "timestamp": "2025-10-07T20:00:34.005990",
        "status": "up",
        "latency": 5.338873,
        "is_best": false
      },
      {
        "timestamp": "2025-10-07T21:00:35.158508",
        "status": "up",
        "latency": 5.532183,
        "is_best": false
      },
      {
        "timestamp": "2025-10-07T22:00:35.422729",
        "status": "up",
        "latency": 4.534079,
        "is_best": false
      },
      {
        "timestamp": "2025-10-08T00:00:23.886730",
        "status": "up",
        "latency": 1.089266,
        "is_best": false
      }
    ],
    "https://www.muou.asia/": [
      {
        "timestamp": "2025-10-07T00:00:37.282989",
        "status": "up",
        "latency": 0.406622,
        "is_best": true
      },
      {
        "timestamp": "2025-10-07T01:00:20.326689",
        "status": "up",
        "latency": 0.497368,
        "is_best": false
      },
      {
        "timestamp": "2025-10-07T02:00:20.228888",
        "status": "up",
        "latency": 0.297677,
        "is_best": true
      },
      {
        "timestamp": "2025-10-07T03:00:26.102001",
        "status": "up",
        "latency": 0.321049,
        "is_best": false
      },
      {
        "timestamp": "2025-10-07T04:00:35.656550",
        "status": "up",
        "latency": 0.340596,
        "is_best": false
      },
      {
        "timestamp": "2025-10-07T05:00:20.460522",
        "status": "up",
        "latency": 0.318603,
        "is_best": true
      },
      {
        "timestamp": "2025-10-07T06:00:20.402500",
        "status": "up",
        "latency": 0.322225,
        "is_best": false
      },
      {
        "timestamp": "2025-10-07T07:00:19.902679",
        "status": "up",
        "latency": 0.382038,
        "is_best": false
      },
      {
        "timestamp": "2025-10-07T08:00:20.228669",
        "status": "up",
        "latency": 0.467008,
        "is_best": false
      },
      {
        "timestamp": "2025-10-07T09:00:24.502149",
        "status": "up",
        "latency": 0.308975,
        "is_best": true
      },
      {
        "timestamp": "2025-10-07T10:00:19.972862",
        "status": "up",
        "latency": 0.300198,
        "is_best": true
      },
      {
        "timestamp": "2025-10-07T11:00:20.624846",
        "status": "up",
        "latency": 0.526011,
        "is_best": false
      },
      {
        "timestamp": "2025-10-07T12:00:22.571614",
        "status": "up",
        "latency": 0.332946,
        "is_best": true
      },
      {
        "timestamp": "2025-10-07T13:00:23.788412",
        "status": "up",
        "latency": 0.9951,
        "is_best": false
      },
      {
        "timestamp": "2025-10-07T14:00:23.823051",
        "status": "up",
        "latency": 1.547144,
        "is_best": false
      },
      {
        "timestamp": "2025-10-07T15:00:24.480258",
        "status": "up",
        "latency": 1.106943,
        "is_best": false
      },
      {
        "timestamp": "2025-10-07T16:00:26.349987",
        "status": "up",
        "latency": 0.568941,
        "is_best": true
      },
      {
        "timestamp": "2025-10-07T17:00:25.777166",
        "status": "up",
        "latency": 2.20284,
        "is_best": false
      },
      {
        "timestamp": "2025-10-07T18:00:29.650938",
        "status": "up",
        "latency": 5.905483,
        "is_best": false
      },
      {
        "timestamp": "2025-10-07T19:01:02.538674",
        "status": "up",
        "latency": 2.221962,
        "is_best": false
      },
      {
        "timestamp": "2025-10-07T20:00:34.005990",
        "status": "up",
        "latency": 2.435325,
        "is_best": true
      },
      {
        "timestamp": "2025-10-07T21:00:35.158508",
        "status": "up",
        "latency": 3.3428,
        "is_best": false
      },
      {
        "timestamp": "2025-10-07T22:00:35.422729",
        "status": "up",
        "latency": 4.841143,
        "is_best": false
      },
      {
        "timestamp": "2025-10-08T00:00:23.886730",
        "status": "up",
        "latency": 0.40974,
        "is_best": true
      }
    ],
    "https://www.muou.site/": [
      {
        "timestamp": "2025-10-07T00:00:37.282989",
        "status": "up",
        "latency": 0.426417,
        "is_best": false
      },
      {
        "timestamp": "2025-10-07T01:00:20.326689",
        "status": "up",
        "latency": 0.325563,
        "is_best": true
      },
      {
        "timestamp": "2025-10-07T02:00:20.228888",
        "status": "up",
        "latency": 0.345498,
        "is_best": false
      },
      {
        "timestamp": "2025-10-07T03:00:26.102001",
        "status": "up",
        "latency": 0.313071,
        "is_best": true
      },
      {
        "timestamp": "2025-10-07T04:00:35.656550",
        "status": "up",
        "latency": 0.35807,
        "is_best": false
      },
      {
        "timestamp": "2025-10-07T05:00:20.460522",
        "status": "up",
        "latency": 0.335296,
        "is_best": false
      },
      {
        "timestamp": "2025-10-07T06:00:20.402500",
        "status": "up",
        "latency": 0.312802,
        "is_best": true
      },
      {
        "timestamp": "2025-10-07T07:00:19.902679",
        "status": "up",
        "latency": 0.345705,
        "is_best": true
      },
      {
        "timestamp": "2025-10-07T08:00:20.228669",
        "status": "up",
        "latency": 0.360038,
        "is_best": false
      },
      {
        "timestamp": "2025-10-07T09:00:24.502149",
        "status": "up",
        "latency": 0.312125,
        "is_best": false
      },
      {
        "timestamp": "2025-10-07T10:00:19.972862",
        "status": "up",
        "latency": 0.388669,
        "is_best": false
      },
      {
        "timestamp": "2025-10-07T11:00:20.624846",
        "status": "up",
        "latency": 0.464823,
        "is_best": true
      },
      {
        "timestamp": "2025-10-07T12:00:22.571614",
        "status": "up",
        "latency": 0.98237,
        "is_best": false
      },
      {
        "timestamp": "2025-10-07T13:00:23.788412",
        "status": "up",
        "latency": 0.330609,
        "is_best": true
      },
      {
        "timestamp": "2025-10-07T14:00:23.823051",
        "status": "up",
        "latency": 0.779668,
        "is_best": true
      },
      {
        "timestamp": "2025-10-07T15:00:24.480258",
        "status": "up",
        "latency": 0.731117,
        "is_best": true
      },
      {
        "timestamp": "2025-10-07T16:00:26.349987",
        "status": "up",
        "latency": 1.933598,
        "is_best": false
      },
      {
        "timestamp": "2025-10-07T17:00:25.777166",
        "status": "up",
        "latency": 0.360878,
        "is_best": true
      },
      {
        "timestamp": "2025-10-07T18:00:29.650938",
        "status": "up",
        "latency": 0.428658,
        "is_best": true
      },
      {
        "timestamp": "2025-10-07T19:01:02.538674",
        "status": "up",
        "latency": 5.521779,
        "is_best": false
      },
      {
        "timestamp": "2025-10-07T20:00:34.005990",
        "status": "up",
        "latency": 4.253088,
        "is_best": false
      },
      {
        "timestamp": "2025-10-07T21:00:35.158508",
        "status": "up",
        "latency": 2.512959,
        "is_best": true
      },
      {
        "timestamp": "2025-10-07T22:00:35.422729",
        "status": "up",
        "latency": 0.668233,
        "is_best": true
      },
      {
        "timestamp": "2025-10-08T00:00:23.886730",
        "status": "up",
        "latency": 0.444772,
        "is_best": false
      }
    ]
  },
  "蜡笔": {
    "https://feimao666.fun": [
      {
        "timestamp": "2025-10-07T00:00:37.282989",
        "status": "up",
        "latency": 0.668725,
        "is_best": false
      },
      {
        "timestamp": "2025-10-07T01:00:20.326689",
        "status": "up",
        "latency": 0.650399,
        "is_best": false
      },
      {
        "timestamp": "2025-10-07T02:00:20.228888",
        "status": "up",
        "latency": 0.67055,
        "is_best": false
      },
      {
        "timestamp": "2025-10-07T03:00:26.102001",
        "status": "up",
        "latency": 0.651757,
        "is_best": false
      },
      {
        "timestamp": "2025-10-07T04:00:35.656550",
        "status": "up",
        "latency": 0.655235,
        "is_best": false
      },
      {
        "timestamp": "2025-10-07T05:00:20.460522",
        "status": "up",
        "latency": 0.679975,
        "is_best": false
      },
      {
        "timestamp": "2025-10-07T06:00:20.402500",
        "status": "up",
        "latency": 0.688529,
        "is_best": false
      },
      {
        "timestamp": "2025-10-07T07:00:19.902679",
        "status": "up",
        "latency": 0.652869,
        "is_best": false
      },
      {
        "timestamp": "2025-10-07T08:00:20.228669",
        "status": "up",
        "latency": 0.637725,
        "is_best": false
      },
      {
        "timestamp": "2025-10-07T09:00:24.502149",
        "status": "up",
        "latency": 0.641912,
        "is_best": false
      },
      {
        "timestamp": "2025-10-07T10:00:19.972862",
        "status": "up",
        "latency": 0.639556,
        "is_best": false
      },
      {
        "timestamp": "2025-10-07T11:00:20.624846",
        "status": "up",
        "latency": 0.649576,
        "is_best": false
      },
      {
        "timestamp": "2025-10-07T12:00:22.571614",
        "status": "up",
        "latency": 0.660812,
        "is_best": false
      },
      {
        "timestamp": "2025-10-07T13:00:23.788412",
        "status": "up",
        "latency": 0.652948,
        "is_best": false
      },
      {
        "timestamp": "2025-10-07T14:00:23.823051",
        "status": "up",
        "latency": 0.655195,
        "is_best": false
      },
      {
        "timestamp": "2025-10-07T15:00:24.480258",
        "status": "up",
        "latency": 0.642287,
        "is_best": false
      },
      {
        "timestamp": "2025-10-07T16:00:26.349987",
        "status": "up",
        "latency": 0.657329,
        "is_best": false
      },
      {
        "timestamp": "2025-10-07T17:00:25.777166",
        "status": "up",
        "latency": 0.651881,
        "is_best": false
      },
      {
        "timestamp": "2025-10-07T18:00:29.650938",
        "status": "up",
        "latency": 0.678755,
        "is_best": false
      },
      {
        "timestamp": "2025-10-07T19:01:02.538674",
        "status": "up",
        "latency": 0.688098,
        "is_best": false
      },
      {
        "timestamp": "2025-10-07T20:00:34.005990",
        "status": "up",
        "latency": 0.658998,
        "is_best": false
      },
      {
        "timestamp": "2025-10-07T21:00:35.158508",
        "status": "up",
        "latency": 0.647917,
        "is_best": false
      },
      {
        "timestamp": "2025-10-07T22:00:35.422729",
        "status": "up",
        "latency": 0.660693,
        "is_best": false
      },
      {
        "timestamp": "2025-10-08T00:00:23.886730",
        "status": "up",
        "latency": 0.681406,
        "is_best": false
      }
    ],
    "http://feimao888.fun": [
      {
        "timestamp": "2025-10-07T00:00:37.282989",
        "status": "up",
        "latency": 0.45691,
        "is_best": true
      },
      {
        "timestamp": "2025-10-07T01:00:20.326689",
        "status": "up",
        "latency": 0.44872,
        "is_best": true
      },
      {
        "timestamp": "2025-10-07T02:00:20.228888",
        "status": "up",
        "latency": 0.414757,
        "is_best": true
      },
      {
        "timestamp": "2025-10-07T03:00:26.102001",
        "status": "up",
        "latency": 0.455235,
        "is_best": true
      },
      {
        "timestamp": "2025-10-07T04:00:35.656550",
        "status": "up",
        "latency": 0.463196,
        "is_best": true
      },
      {
        "timestamp": "2025-10-07T05:00:20.460522",
        "status": "up",
        "latency": 0.420201,
        "is_best": true
      },
      {
        "timestamp": "2025-10-07T06:00:20.402500",
        "status": "up",
        "latency": 0.448145,
        "is_best": true
      },
      {
        "timestamp": "2025-10-07T07:00:19.902679",
        "status": "up",
        "latency": 0.46122,
        "is_best": true
      },
      {
        "timestamp": "2025-10-07T08:00:20.228669",
        "status": "up",
        "latency": 0.43885,
        "is_best": true
      },
      {
        "timestamp": "2025-10-07T09:00:24.502149",
        "status": "up",
        "latency": 0.448432,
        "is_best": true
      },
      {
        "timestamp": "2025-10-07T10:00:19.972862",
        "status": "up",
        "latency": 0.434025,
        "is_best": true
      },
      {
        "timestamp": "2025-10-07T11:00:20.624846",
        "status": "up",
        "latency": 0.42797,
        "is_best": true
      },
      {
        "timestamp": "2025-10-07T12:00:22.571614",
        "status": "up",
        "latency": 0.482466,
        "is_best": true
      },
      {
        "timestamp": "2025-10-07T13:00:23.788412",
        "status": "up",
        "latency": 0.429565,
        "is_best": true
      },
      {
        "timestamp": "2025-10-07T14:00:23.823051",
        "status": "up",
        "latency": 0.441167,
        "is_best": true
      },
      {
        "timestamp": "2025-10-07T15:00:24.480258",
        "status": "up",
        "latency": 0.408155,
        "is_best": true
      },
      {
        "timestamp": "2025-10-07T16:00:26.349987",
        "status": "up",
        "latency": 0.449334,
        "is_best": true
      },
      {
        "timestamp": "2025-10-07T17:00:25.777166",
        "status": "up",
        "latency": 0.446621,
        "is_best": true
      },
      {
        "timestamp": "2025-10-07T18:00:29.650938",
        "status": "up",
        "latency": 0.419383,
        "is_best": true
      },
      {
        "timestamp": "2025-10-07T19:01:02.538674",
        "status": "up",
        "latency": 0.4405,
        "is_best": true
      },
      {
        "timestamp": "2025-10-07T20:00:34.005990",
        "status": "up",
        "latency": 0.391767,
        "is_best": true
      },
      {
        "timestamp": "2025-10-07T21:00:35.158508",
        "status": "up",
        "latency": 0.441883,
        "is_best": true
      },
      {
        "timestamp": "2025-10-07T22:00:35.422729",
        "status": "up",
        "latency": 0.423068,
        "is_best": true
      },
      {
        "timestamp": "2025-10-08T00:00:23.886730",
        "status": "up",
        "latency": 0.461047,
        "is_best": true
      }
    ]
  },
  "至臻": {
    "https://mihdr.top": [
      {
        "timestamp": "2025-10-07T00:00:37.282989",
        "status": "down",
        "latency": null,
        "is_best": false,
        "error_detail": "超时"
      },
      {
        "timestamp": "2025-10-07T01:00:20.326689",
        "status": "up",
        "latency": 0.194383,
        "is_best": true
      },
      {
        "timestamp": "2025-10-07T02:00:20.228888",
        "status": "up",
        "latency": 0.38808,
        "is_best": false
      },
      {
        "timestamp": "2025-10-07T03:00:26.102001",
        "status": "up",
        "latency": 0.198788,
        "is_best": false
      },
      {
        "timestamp": "2025-10-07T04:00:35.656550",
        "status": "down",
        "latency": null,
        "is_best": false,
        "error_detail": "超时"
      },
      {
        "timestamp": "2025-10-07T05:00:20.460522",
        "status": "up",
        "latency": 0.263996,
        "is_best": true
      },
      {
        "timestamp": "2025-10-07T06:00:20.402500",
        "status": "up",
        "latency": 0.270017,
        "is_best": true
      },
      {
        "timestamp": "2025-10-07T07:00:19.902679",
        "status": "up",
        "latency": 0.205301,
        "is_best": true
      },
      {
        "timestamp": "2025-10-07T08:00:20.228669",
        "status": "up",
        "latency": 0.269659,
        "is_best": true
      },
      {
        "timestamp": "2025-10-07T09:00:24.502149",
        "status": "up",
        "latency": 0.330174,
        "is_best": false
      },
      {
        "timestamp": "2025-10-07T10:00:19.972862",
        "status": "up",
        "latency": 0.286182,
        "is_best": false
      },
      {
        "timestamp": "2025-10-07T11:00:20.624846",
        "status": "up",
        "latency": 0.267656,
        "is_best": true
      },
      {
        "timestamp": "2025-10-07T12:00:22.571614",
        "status": "up",
        "latency": 0.29169,
        "is_best": false
      },
      {
        "timestamp": "2025-10-07T13:00:23.788412",
        "status": "up",
        "latency": 0.265984,
        "is_best": true
      },
      {
        "timestamp": "2025-10-07T14:00:23.823051",
        "status": "up",
        "latency": 0.185324,
        "is_best": true
      },
      {
        "timestamp": "2025-10-07T15:00:24.480258",
        "status": "up",
        "latency": 0.28653,
        "is_best": false
      },
      {
        "timestamp": "2025-10-07T16:00:26.349987",
        "status": "up",
        "latency": 0.50473,
        "is_best": false
      },
      {
        "timestamp": "2025-10-07T17:00:25.777166",
        "status": "up",
        "latency": 0.311917,
        "is_best": false
      },
      {
        "timestamp": "2025-10-07T18:00:29.650938",
        "status": "up",
        "latency": 0.315683,
        "is_best": false
      },
      {
        "timestamp": "2025-10-07T19:01:02.538674",
        "status": "up",
        "latency": 1.540242,
        "is_best": false
      },
      {
        "timestamp": "2025-10-07T20:00:34.005990",
        "status": "up",
        "latency": 0.271933,
        "is_best": false
      },
      {
        "timestamp": "2025-10-07T21:00:35.158508",
        "status": "up",
        "latency": 0.355433,
        "is_best": false
      },
      {
        "timestamp": "2025-10-07T22:00:35.422729",
        "status": "up",
        "latency": 0.366123,
        "is_best": false
      },
      {
        "timestamp": "2025-10-08T00:00:23.886730",
        "status": "up",
        "latency": 0.264349,
        "is_best": false
      }
    ],
    "http://www.miqk.cc": [
      {
        "timestamp": "2025-10-07T00:00:37.282989",
        "status": "up",
        "latency": 0.355263,
        "is_best": false
      },
      {
        "timestamp": "2025-10-07T01:00:20.326689",
        "status": "up",
        "latency": 0.263703,
        "is_best": false
      },
      {
        "timestamp": "2025-10-07T02:00:20.228888",
        "status": "up",
        "latency": 0.322721,
        "is_best": false
      },
      {
        "timestamp": "2025-10-07T03:00:26.102001",
        "status": "up",
        "latency": 0.227527,
        "is_best": false
      },
      {
        "timestamp": "2025-10-07T04:00:35.656550",
        "status": "up",
        "latency": 0.227288,
        "is_best": true
      },
      {
        "timestamp": "2025-10-07T05:00:20.460522",
        "status": "up",
        "latency": 0.284454,
        "is_best": false
      },
      {
        "timestamp": "2025-10-07T06:00:20.402500",
        "status": "up",
        "latency": 0.286602,
        "is_best": false
      },
      {
        "timestamp": "2025-10-07T07:00:19.902679",
        "status": "up",
        "latency": 0.230007,
        "is_best": false
      },
      {
        "timestamp": "2025-10-07T08:00:20.228669",
        "status": "up",
        "latency": 0.324655,
        "is_best": false
      },
      {
        "timestamp": "2025-10-07T09:00:24.502149",
        "status": "up",
        "latency": 0.22177,
        "is_best": true
      },
      {
        "timestamp": "2025-10-07T10:00:19.972862",
        "status": "up",
        "latency": 0.227449,
        "is_best": true
      },
      {
        "timestamp": "2025-10-07T11:00:20.624846",
        "status": "up",
        "latency": 0.284077,
        "is_best": false
      },
      {
        "timestamp": "2025-10-07T12:00:22.571614",
        "status": "up",
        "latency": 0.226604,
        "is_best": false
      },
      {
        "timestamp": "2025-10-07T13:00:23.788412",
        "status": "up",
        "latency": 0.409928,
        "is_best": false
      },
      {
        "timestamp": "2025-10-07T14:00:23.823051",
        "status": "up",
        "latency": 0.571587,
        "is_best": false
      },
      {
        "timestamp": "2025-10-07T15:00:24.480258",
        "status": "up",
        "latency": 0.292761,
        "is_best": false
      },
      {
        "timestamp": "2025-10-07T16:00:26.349987",
        "status": "up",
        "latency": 0.294231,
        "is_best": false
      },
      {
        "timestamp": "2025-10-07T17:00:25.777166",
        "status": "up",
        "latency": 0.225245,
        "is_best": false
      },
      {
        "timestamp": "2025-10-07T18:00:29.650938",
        "status": "up",
        "latency": 0.299775,
        "is_best": false
      },
      {
        "timestamp": "2025-10-07T19:01:02.538674",
        "status": "up",
        "latency": 2.476578,
        "is_best": false
      },
      {
        "timestamp": "2025-10-07T20:00:34.005990",
        "status": "up",
        "latency": 0.440782,
        "is_best": false
      },
      {
        "timestamp": "2025-10-07T21:00:35.158508",
        "status": "up",
        "latency": 0.291351,
        "is_best": true
      },
      {
        "timestamp": "2025-10-07T22:00:35.422729",
        "status": "up",
        "latency": 0.235315,
        "is_best": false
      },
      {
        "timestamp": "2025-10-08T00:00:23.886730",
        "status": "up",
        "latency": 0.293038,
        "is_best": false
      }
    ],
    "https://www.mihdr.top/": [
      {
        "timestamp": "2025-10-07T00:00:37.282989",
        "status": "up",
        "latency": 0.287651,
        "is_best": true
      },
      {
        "timestamp": "2025-10-07T01:00:20.326689",
        "status": "up",
        "latency": 0.201728,
        "is_best": false
      },
      {
        "timestamp": "2025-10-07T02:00:20.228888",
        "status": "up",
        "latency": 0.273241,
        "is_best": true
      },
      {
        "timestamp": "2025-10-07T03:00:26.102001",
        "status": "up",
        "latency": 0.195599,
        "is_best": true
      },
      {
        "timestamp": "2025-10-07T04:00:35.656550",
        "status": "up",
        "latency": 0.367532,
        "is_best": false
      },
      {
        "timestamp": "2025-10-07T05:00:20.460522",
        "status": "up",
        "latency": 0.272796,
        "is_best": false
      },
      {
        "timestamp": "2025-10-07T06:00:20.402500",
        "status": "up",
        "latency": 0.315166,
        "is_best": false
      },
      {
        "timestamp": "2025-10-07T07:00:19.902679",
        "status": "up",
        "latency": 0.317074,
        "is_best": false
      },
      {
        "timestamp": "2025-10-07T08:00:20.228669",
        "status": "up",
        "latency": 0.618965,
        "is_best": false
      },
      {
        "timestamp": "2025-10-07T09:00:24.502149",
        "status": "up",
        "latency": 0.321778,
        "is_best": false
      },
      {
        "timestamp": "2025-10-07T10:00:19.972862",
        "status": "up",
        "latency": 0.231398,
        "is_best": false
      },
      {
        "timestamp": "2025-10-07T11:00:20.624846",
        "status": "up",
        "latency": 0.319429,
        "is_best": false
      },
      {
        "timestamp": "2025-10-07T12:00:22.571614",
        "status": "up",
        "latency": 0.32188,
        "is_best": false
      },
      {
        "timestamp": "2025-10-07T13:00:23.788412",
        "status": "up",
        "latency": 0.302789,
        "is_best": false
      },
      {
        "timestamp": "2025-10-07T14:00:23.823051",
        "status": "up",
        "latency": 0.200704,
        "is_best": false
      },
      {
        "timestamp": "2025-10-07T15:00:24.480258",
        "status": "up",
        "latency": 0.263377,
        "is_best": false
      },
      {
        "timestamp": "2025-10-07T16:00:26.349987",
        "status": "up",
        "latency": 0.350429,
        "is_best": false
      },
      {
        "timestamp": "2025-10-07T17:00:25.777166",
        "status": "up",
        "latency": 0.320487,
        "is_best": false
      },
      {
        "timestamp": "2025-10-07T18:00:29.650938",
        "status": "up",
        "latency": 0.27022,
        "is_best": false
      },
      {
        "timestamp": "2025-10-07T19:01:02.538674",
        "status": "up",
        "latency": 2.239579,
        "is_best": false
      },
      {
        "timestamp": "2025-10-07T20:00:34.005990",
        "status": "up",
        "latency": 0.304021,
        "is_best": false
      },
      {
        "timestamp": "2025-10-07T21:00:35.158508",
        "status": "up",
        "latency": 0.330273,
        "is_best": false
      },
      {
        "timestamp": "2025-10-07T22:00:35.422729",
        "status": "up",
        "latency": 0.375882,
        "is_best": false
      },
      {
        "timestamp": "2025-10-08T00:00:23.886730",
        "status": "up",
        "latency": 0.288258,
        "is_best": false
      }
    ],
    "https://www.zhizhenpan.fun/": [
      {
        "timestamp": "2025-10-07T00:00:37.282989",
        "status": "up",
        "latency": 0.34284,
        "is_best": false
      },
      {
        "timestamp": "2025-10-07T01:00:20.326689",
        "status": "up",
        "latency": 0.28361,
        "is_best": false
      },
      {
        "timestamp": "2025-10-07T02:00:20.228888",
        "status": "up",
        "latency": 0.274227,
        "is_best": false
      },
      {
        "timestamp": "2025-10-07T03:00:26.102001",
        "status": "up",
        "latency": 0.535203,
        "is_best": false
      },
      {
        "timestamp": "2025-10-07T04:00:35.656550",
        "status": "up",
        "latency": 0.336368,
        "is_best": false
      },
      {
        "timestamp": "2025-10-07T05:00:20.460522",
        "status": "up",
        "latency": 0.365533,
        "is_best": false
      },
      {
        "timestamp": "2025-10-07T06:00:20.402500",
        "status": "up",
        "latency": 0.336536,
        "is_best": false
      },
      {
        "timestamp": "2025-10-07T07:00:19.902679",
        "status": "up",
        "latency": 0.392584,
        "is_best": false
      },
      {
        "timestamp": "2025-10-07T08:00:20.228669",
        "status": "up",
        "latency": 0.281906,
        "is_best": false
      },
      {
        "timestamp": "2025-10-07T09:00:24.502149",
        "status": "up",
        "latency": 0.332371,
        "is_best": false
      },
      {
        "timestamp": "2025-10-07T10:00:19.972862",
        "status": "up",
        "latency": 0.329535,
        "is_best": false
      },
      {
        "timestamp": "2025-10-07T11:00:20.624846",
        "status": "up",
        "latency": 0.31745,
        "is_best": false
      },
      {
        "timestamp": "2025-10-07T12:00:22.571614",
        "status": "up",
        "latency": 0.192085,
        "is_best": true
      },
      {
        "timestamp": "2025-10-07T13:00:23.788412",
        "status": "up",
        "latency": 0.267499,
        "is_best": false
      },
      {
        "timestamp": "2025-10-07T14:00:23.823051",
        "status": "up",
        "latency": 0.200791,
        "is_best": false
      },
      {
        "timestamp": "2025-10-07T15:00:24.480258",
        "status": "up",
        "latency": 0.257774,
        "is_best": true
      },
      {
        "timestamp": "2025-10-07T16:00:26.349987",
        "status": "up",
        "latency": 0.240342,
        "is_best": true
      },
      {
        "timestamp": "2025-10-07T17:00:25.777166",
        "status": "up",
        "latency": 0.196836,
        "is_best": true
      },
      {
        "timestamp": "2025-10-07T18:00:29.650938",
        "status": "up",
        "latency": 0.20165,
        "is_best": true
      },
      {
        "timestamp": "2025-10-07T19:01:02.538674",
        "status": "up",
        "latency": 0.201641,
        "is_best": true
      },
      {
        "timestamp": "2025-10-07T20:00:34.005990",
        "status": "up",
        "latency": 0.204173,
        "is_best": true
      },
      {
        "timestamp": "2025-10-07T21:00:35.158508",
        "status": "up",
        "latency": 0.344556,
        "is_best": false
      },
      {
        "timestamp": "2025-10-07T22:00:35.422729",
        "status": "up",
        "latency": 0.212144,
        "is_best": true
      },
      {
        "timestamp": "2025-10-08T00:00:23.886730",
        "status": "up",
        "latency": 0.206224,
        "is_best": true
      }
    ]
  },
  "多多": {
    "https://tv.yydsys.top": [
      {
        "timestamp": "2025-10-07T00:00:37.282989",
        "status": "up",
        "latency": 0.795507,
        "is_best": false
      },
      {
        "timestamp": "2025-10-07T01:00:20.326689",
        "status": "up",
        "latency": 0.807583,
        "is_best": false
      },
      {
        "timestamp": "2025-10-07T02:00:20.228888",
        "status": "up",
        "latency": 0.506483,
        "is_best": true
      },
      {
        "timestamp": "2025-10-07T03:00:26.102001",
        "status": "up",
        "latency": 0.508587,
        "is_best": true
      },
      {
        "timestamp": "2025-10-07T04:00:35.656550",
        "status": "up",
        "latency": 0.502676,
        "is_best": true
      },
      {
        "timestamp": "2025-10-07T05:00:20.460522",
        "status": "up",
        "latency": 0.450665,
        "is_best": true
      },
      {
        "timestamp": "2025-10-07T06:00:20.402500",
        "status": "up",
        "latency": 0.573646,
        "is_best": true
      },
      {
        "timestamp": "2025-10-07T07:00:19.902679",
        "status": "up",
        "latency": 0.448768,
        "is_best": true
      },
      {
        "timestamp": "2025-10-07T08:00:20.228669",
        "status": "up",
        "latency": 0.509453,
        "is_best": true
      },
      {
        "timestamp": "2025-10-07T09:00:24.502149",
        "status": "up",
        "latency": 0.524474,
        "is_best": true
      },
      {
        "timestamp": "2025-10-07T10:00:19.972862",
        "status": "up",
        "latency": 0.536035,
        "is_best": false
      },
      {
        "timestamp": "2025-10-07T11:00:20.624846",
        "status": "up",
        "latency": 0.550805,
        "is_best": false
      },
      {
        "timestamp": "2025-10-07T12:00:22.571614",
        "status": "up",
        "latency": 0.562497,
        "is_best": false
      },
      {
        "timestamp": "2025-10-07T13:00:23.788412",
        "status": "up",
        "latency": 0.510745,
        "is_best": true
      },
      {
        "timestamp": "2025-10-07T14:00:23.823051",
        "status": "up",
        "latency": 0.629653,
        "is_best": false
      },
      {
        "timestamp": "2025-10-07T15:00:24.480258",
        "status": "up",
        "latency": 0.819463,
        "is_best": false
      },
      {
        "timestamp": "2025-10-07T16:00:26.349987",
        "status": "up",
        "latency": 0.478209,
        "is_best": true
      },
      {
        "timestamp": "2025-10-07T17:00:25.777166",
        "status": "up",
        "latency": 0.508721,
        "is_best": true
      },
      {
        "timestamp": "2025-10-07T18:00:29.650938",
        "status": "up",
        "latency": 0.455588,
        "is_best": true
      },
      {
        "timestamp": "2025-10-07T19:01:02.538674",
        "status": "up",
        "latency": 1.813797,
        "is_best": true
      },
      {
        "timestamp": "2025-10-07T20:00:34.005990",
        "status": "up",
        "latency": 0.473596,
        "is_best": true
      },
      {
        "timestamp": "2025-10-07T21:00:35.158508",
        "status": "up",
        "latency": 0.759386,
        "is_best": false
      },
      {
        "timestamp": "2025-10-07T22:00:35.422729",
        "status": "up",
        "latency": 1.860894,
        "is_best": false
      },
      {
        "timestamp": "2025-10-08T00:00:23.886730",
        "status": "up",
        "latency": 0.848597,
        "is_best": false
      }
    ],
    "https://tv.yydsys.cc": [
      {
        "timestamp": "2025-10-07T00:00:37.282989",
        "status": "up",
        "latency": 0.656074,
        "is_best": true
      },
      {
        "timestamp": "2025-10-07T01:00:20.326689",
        "status": "up",
        "latency": 0.688051,
        "is_best": true
      },
      {
        "timestamp": "2025-10-07T02:00:20.228888",
        "status": "up",
        "latency": 0.651655,
        "is_best": false
      },
      {
        "timestamp": "2025-10-07T03:00:26.102001",
        "status": "up",
        "latency": 0.687321,
        "is_best": false
      },
      {
        "timestamp": "2025-10-07T04:00:35.656550",
        "status": "up",
        "latency": 0.672947,
        "is_best": false
      },
      {
        "timestamp": "2025-10-07T05:00:20.460522",
        "status": "up",
        "latency": 0.68124,
        "is_best": false
      },
      {
        "timestamp": "2025-10-07T06:00:20.402500",
        "status": "up",
        "latency": 0.64584,
        "is_best": false
      },
      {
        "timestamp": "2025-10-07T07:00:19.902679",
        "status": "up",
        "latency": 0.705791,
        "is_best": false
      },
      {
        "timestamp": "2025-10-07T08:00:20.228669",
        "status": "up",
        "latency": 0.653418,
        "is_best": false
      },
      {
        "timestamp": "2025-10-07T09:00:24.502149",
        "status": "up",
        "latency": 0.633973,
        "is_best": false
      },
      {
        "timestamp": "2025-10-07T10:00:19.972862",
        "status": "up",
        "latency": 0.702972,
        "is_best": false
      },
      {
        "timestamp": "2025-10-07T11:00:20.624846",
        "status": "up",
        "latency": 0.635118,
        "is_best": false
      },
      {
        "timestamp": "2025-10-07T12:00:22.571614",
        "status": "up",
        "latency": 0.633028,
        "is_best": false
      },
      {
        "timestamp": "2025-10-07T13:00:23.788412",
        "status": "up",
        "latency": 0.638082,
        "is_best": false
      },
      {
        "timestamp": "2025-10-07T14:00:23.823051",
        "status": "up",
        "latency": 0.628436,
        "is_best": false
      },
      {
        "timestamp": "2025-10-07T15:00:24.480258",
        "status": "up",
        "latency": 0.675815,
        "is_best": true
      },
      {
        "timestamp": "2025-10-07T16:00:26.349987",
        "status": "up",
        "latency": 0.663326,
        "is_best": false
      },
      {
        "timestamp": "2025-10-07T17:00:25.777166",
        "status": "up",
        "latency": 0.649983,
        "is_best": false
      },
      {
        "timestamp": "2025-10-07T18:00:29.650938",
        "status": "up",
        "latency": 0.645229,
        "is_best": false
      },
      {
        "timestamp": "2025-10-07T19:01:02.538674",
        "status": "up",
        "latency": 6.877761,
        "is_best": false
      },
      {
        "timestamp": "2025-10-07T20:00:34.005990",
        "status": "up",
        "latency": 0.849881,
        "is_best": false
      },
      {
        "timestamp": "2025-10-07T21:00:35.158508",
        "status": "up",
        "latency": 0.653179,
        "is_best": true
      },
      {
        "timestamp": "2025-10-07T22:00:35.422729",
        "status": "up",
        "latency": 0.663974,
        "is_best": true
      },
      {
        "timestamp": "2025-10-08T00:00:23.886730",
        "status": "up",
        "latency": 0.659672,
        "is_best": true
      }
    ],
    "https://tv.214521.xyz": [
      {
        "timestamp": "2025-10-07T00:00:37.282989",
        "status": "up",
        "latency": 0.764294,
        "is_best": false
      },
      {
        "timestamp": "2025-10-07T01:00:20.326689",
        "status": "up",
        "latency": 1.143491,
        "is_best": false
      },
      {
        "timestamp": "2025-10-07T02:00:20.228888",
        "status": "up",
        "latency": 0.567159,
        "is_best": false
      },
      {
        "timestamp": "2025-10-07T03:00:26.102001",
        "status": "up",
        "latency": 0.698648,
        "is_best": false
      },
      {
        "timestamp": "2025-10-07T04:00:35.656550",
        "status": "up",
        "latency": 0.654929,
        "is_best": false
      },
      {
        "timestamp": "2025-10-07T05:00:20.460522",
        "status": "up",
        "latency": 0.561053,
        "is_best": false
      },
      {
        "timestamp": "2025-10-07T06:00:20.402500",
        "status": "up",
        "latency": 0.756609,
        "is_best": false
      },
      {
        "timestamp": "2025-10-07T07:00:19.902679",
        "status": "up",
        "latency": 0.537311,
        "is_best": false
      },
      {
        "timestamp": "2025-10-07T08:00:20.228669",
        "status": "up",
        "latency": 0.545107,
        "is_best": false
      },
      {
        "timestamp": "2025-10-07T09:00:24.502149",
        "status": "up",
        "latency": 0.664874,
        "is_best": false
      },
      {
        "timestamp": "2025-10-07T10:00:19.972862",
        "status": "up",
        "latency": 0.507344,
        "is_best": true
      },
      {
        "timestamp": "2025-10-07T11:00:20.624846",
        "status": "up",
        "latency": 0.505143,
        "is_best": true
      },
      {
        "timestamp": "2025-10-07T12:00:22.571614",
        "status": "up",
        "latency": 0.503819,
        "is_best": true
      },
      {
        "timestamp": "2025-10-07T13:00:23.788412",
        "status": "up",
        "latency": 0.533907,
        "is_best": false
      },
      {
        "timestamp": "2025-10-07T14:00:23.823051",
        "status": "up",
        "latency": 0.583469,
        "is_best": true
      },
      {
        "timestamp": "2025-10-07T15:00:24.480258",
        "status": "up",
        "latency": 0.736711,
        "is_best": false
      },
      {
        "timestamp": "2025-10-07T16:00:26.349987",
        "status": "up",
        "latency": 0.524419,
        "is_best": false
      },
      {
        "timestamp": "2025-10-07T17:00:25.777166",
        "status": "up",
        "latency": 0.517813,
        "is_best": false
      },
      {
        "timestamp": "2025-10-07T18:00:29.650938",
        "status": "up",
        "latency": 0.461804,
        "is_best": false
      },
      {
        "timestamp": "2025-10-07T19:01:02.538674",
        "status": "up",
        "latency": 1.949915,
        "is_best": false
      },
      {
        "timestamp": "2025-10-07T20:00:34.005990",
        "status": "up",
        "latency": 0.589919,
        "is_best": false
      },
      {
        "timestamp": "2025-10-07T21:00:35.158508",
        "status": "up",
        "latency": 0.695369,
        "is_best": false
      },
      {
        "timestamp": "2025-10-07T22:00:35.422729",
        "status": "up",
        "latency": 1.565781,
        "is_best": false
      },
      {
        "timestamp": "2025-10-08T00:00:23.886730",
        "status": "up",
        "latency": 1.841931,
        "is_best": false
      }
    ]
  },
  "欧哥": {
    "https://woog.nxog.eu.org": [
      {
        "timestamp": "2025-10-07T00:00:37.282989",
        "status": "up",
        "latency": 0.780741,
        "is_best": true
      },
      {
        "timestamp": "2025-10-07T01:00:20.326689",
        "status": "up",
        "latency": 0.777659,
        "is_best": true
      },
      {
        "timestamp": "2025-10-07T02:00:20.228888",
        "status": "up",
        "latency": 0.64976,
        "is_best": true
      },
      {
        "timestamp": "2025-10-07T03:00:26.102001",
        "status": "up",
        "latency": 0.803468,
        "is_best": true
      },
      {
        "timestamp": "2025-10-07T04:00:35.656550",
        "status": "up",
        "latency": 0.611291,
        "is_best": true
      },
      {
        "timestamp": "2025-10-07T05:00:20.460522",
        "status": "up",
        "latency": 0.795713,
        "is_best": true
      },
      {
        "timestamp": "2025-10-07T06:00:20.402500",
        "status": "up",
        "latency": 0.618783,
        "is_best": true
      },
      {
        "timestamp": "2025-10-07T07:00:19.902679",
        "status": "up",
        "latency": 0.641881,
        "is_best": true
      },
      {
        "timestamp": "2025-10-07T08:00:20.228669",
        "status": "up",
        "latency": 0.633893,
        "is_best": true
      },
      {
        "timestamp": "2025-10-07T09:00:24.502149",
        "status": "up",
        "latency": 0.631387,
        "is_best": true
      },
      {
        "timestamp": "2025-10-07T10:00:19.972862",
        "status": "up",
        "latency": 0.754524,
        "is_best": true
      },
      {
        "timestamp": "2025-10-07T11:00:20.624846",
        "status": "up",
        "latency": 0.762917,
        "is_best": true
      },
      {
        "timestamp": "2025-10-07T12:00:22.571614",
        "status": "up",
        "latency": 0.634514,
        "is_best": true
      },
      {
        "timestamp": "2025-10-07T13:00:23.788412",
        "status": "up",
        "latency": 0.762895,
        "is_best": true
      },
      {
        "timestamp": "2025-10-07T14:00:23.823051",
        "status": "up",
        "latency": 0.605183,
        "is_best": true
      },
      {
        "timestamp": "2025-10-07T15:00:24.480258",
        "status": "up",
        "latency": 0.762454,
        "is_best": true
      },
      {
        "timestamp": "2025-10-07T16:00:26.349987",
        "status": "up",
        "latency": 0.750078,
        "is_best": true
      },
      {
        "timestamp": "2025-10-07T17:00:25.777166",
        "status": "up",
        "latency": 0.771047,
        "is_best": true
      },
      {
        "timestamp": "2025-10-07T18:00:29.650938",
        "status": "up",
        "latency": 0.790229,
        "is_best": true
      },
      {
        "timestamp": "2025-10-07T19:01:02.538674",
        "status": "up",
        "latency": 1.78629,
        "is_best": true
      },
      {
        "timestamp": "2025-10-07T20:00:34.005990",
        "status": "up",
        "latency": 0.78737,
        "is_best": true
      },
      {
        "timestamp": "2025-10-07T21:00:35.158508",
        "status": "up",
        "latency": 0.617069,
        "is_best": true
      },
      {
        "timestamp": "2025-10-07T22:00:35.422729",
        "status": "up",
        "latency": 0.853924,
        "is_best": true
      },
      {
        "timestamp": "2025-10-08T00:00:23.886730",
        "status": "up",
        "latency": 0.785038,
        "is_best": true
      }
    ]
  },
  "二小": {
    "https://xhww.net": [
      {
        "timestamp": "2025-10-07T00:00:37.282989",
        "status": "up",
        "latency": 0.932365,
        "is_best": false
      },
      {
        "timestamp": "2025-10-07T01:00:20.326689",
        "status": "up",
        "latency": 0.950884,
        "is_best": false
      },
      {
        "timestamp": "2025-10-07T02:00:20.228888",
        "status": "up",
        "latency": 0.967431,
        "is_best": false
      },
      {
        "timestamp": "2025-10-07T03:00:26.102001",
        "status": "up",
        "latency": 0.974283,
        "is_best": false
      },
      {
        "timestamp": "2025-10-07T04:00:35.656550",
        "status": "up",
        "latency": 0.934161,
        "is_best": false
      },
      {
        "timestamp": "2025-10-07T05:00:20.460522",
        "status": "up",
        "latency": 0.960963,
        "is_best": false
      },
      {
        "timestamp": "2025-10-07T06:00:20.402500",
        "status": "up",
        "latency": 0.983221,
        "is_best": false
      },
      {
        "timestamp": "2025-10-07T07:00:19.902679",
        "status": "up",
        "latency": 0.931826,
        "is_best": false
      },
      {
        "timestamp": "2025-10-07T08:00:20.228669",
        "status": "up",
        "latency": 0.957459,
        "is_best": false
      },
      {
        "timestamp": "2025-10-07T09:00:24.502149",
        "status": "up",
        "latency": 0.767596,
        "is_best": false
      },
      {
        "timestamp": "2025-10-07T10:00:19.972862",
        "status": "up",
        "latency": 0.951882,
        "is_best": false
      },
      {
        "timestamp": "2025-10-07T11:00:20.624846",
        "status": "up",
        "latency": 0.944849,
        "is_best": false
      },
      {
        "timestamp": "2025-10-07T12:00:22.571614",
        "status": "up",
        "latency": 0.962,
        "is_best": false
      },
      {
        "timestamp": "2025-10-07T13:00:23.788412",
        "status": "up",
        "latency": 0.933451,
        "is_best": false
      },
      {
        "timestamp": "2025-10-07T14:00:23.823051",
        "status": "up",
        "latency": 0.973483,
        "is_best": false
      },
      {
        "timestamp": "2025-10-07T15:00:24.480258",
        "status": "up",
        "latency": 0.792095,
        "is_best": false
      },
      {
        "timestamp": "2025-10-07T16:00:26.349987",
        "status": "up",
        "latency": 0.951419,
        "is_best": false
      },
      {
        "timestamp": "2025-10-07T17:00:25.777166",
        "status": "up",
        "latency": 0.968204,
        "is_best": false
      },
      {
        "timestamp": "2025-10-07T18:00:29.650938",
        "status": "up",
        "latency": 0.980313,
        "is_best": false
      },
      {
        "timestamp": "2025-10-07T19:01:02.538674",
        "status": "up",
        "latency": 0.76245,
        "is_best": false
      },
      {
        "timestamp": "2025-10-07T20:00:34.005990",
        "status": "up",
        "latency": 2.145172,
        "is_best": false
      },
      {
        "timestamp": "2025-10-07T21:00:35.158508",
        "status": "up",
        "latency": 3.546812,
        "is_best": false
      },
      {
        "timestamp": "2025-10-07T22:00:35.422729",
        "status": "up",
        "latency": 2.646703,
        "is_best": false
      },
      {
        "timestamp": "2025-10-08T00:00:23.886730",
        "status": "up",
        "latency": 0.972751,
        "is_best": false
      }
    ],
    "http://2xiaopan.fun": [
      {
        "timestamp": "2025-10-07T00:00:37.282989",
        "status": "up",
        "latency": 0.955626,
        "is_best": false
      },
      {
        "timestamp": "2025-10-07T01:00:20.326689",
        "status": "up",
        "latency": 0.494355,
        "is_best": true
      },
      {
        "timestamp": "2025-10-07T02:00:20.228888",
        "status": "up",
        "latency": 0.669324,
        "is_best": true
      },
      {
        "timestamp": "2025-10-07T03:00:26.102001",
        "status": "up",
        "latency": 0.746486,
        "is_best": true
      },
      {
        "timestamp": "2025-10-07T04:00:35.656550",
        "status": "up",
        "latency": 0.781648,
        "is_best": true
      },
      {
        "timestamp": "2025-10-07T05:00:20.460522",
        "status": "up",
        "latency": 0.726674,
        "is_best": true
      },
      {
        "timestamp": "2025-10-07T06:00:20.402500",
        "status": "up",
        "latency": 0.743687,
        "is_best": true
      },
      {
        "timestamp": "2025-10-07T07:00:19.902679",
        "status": "up",
        "latency": 0.745471,
        "is_best": true
      },
      {
        "timestamp": "2025-10-07T08:00:20.228669",
        "status": "up",
        "latency": 0.158787,
        "is_best": true
      },
      {
        "timestamp": "2025-10-07T09:00:24.502149",
        "status": "up",
        "latency": 0.671163,
        "is_best": true
      },
      {
        "timestamp": "2025-10-07T10:00:19.972862",
        "status": "up",
        "latency": 0.659755,
        "is_best": true
      },
      {
        "timestamp": "2025-10-07T11:00:20.624846",
        "status": "down",
        "latency": null,
        "is_best": false,
        "error_detail": "连接失败"
      },
      {
        "timestamp": "2025-10-07T12:00:22.571614",
        "status": "up",
        "latency": 0.14189,
        "is_best": true
      },
      {
        "timestamp": "2025-10-07T13:00:23.788412",
        "status": "up",
        "latency": 0.772655,
        "is_best": false
      },
      {
        "timestamp": "2025-10-07T14:00:23.823051",
        "status": "up",
        "latency": 0.497467,
        "is_best": true
      },
      {
        "timestamp": "2025-10-07T15:00:24.480258",
        "status": "up",
        "latency": 0.720179,
        "is_best": true
      },
      {
        "timestamp": "2025-10-07T16:00:26.349987",
        "status": "up",
        "latency": 0.525395,
        "is_best": true
      },
      {
        "timestamp": "2025-10-07T17:00:25.777166",
        "status": "up",
        "latency": 0.524026,
        "is_best": true
      },
      {
        "timestamp": "2025-10-07T18:00:29.650938",
        "status": "up",
        "latency": 0.750381,
        "is_best": true
      },
      {
        "timestamp": "2025-10-07T19:01:02.538674",
        "status": "up",
        "latency": 0.493683,
        "is_best": true
      },
      {
        "timestamp": "2025-10-07T20:00:34.005990",
        "status": "up",
        "latency": 1.004363,
        "is_best": false
      },
      {
        "timestamp": "2025-10-07T21:00:35.158508",
        "status": "down",
        "latency": null,
        "is_best": false,
        "error_detail": "连接失败"
      },
      {
        "timestamp": "2025-10-07T22:00:35.422729",
        "status": "up",
        "latency": 0.792092,
        "is_best": true
      },
      {
        "timestamp": "2025-10-08T00:00:23.886730",
        "status": "up",
        "latency": 0.718126,
        "is_best": true
      }
    ],
    "https://erxiaofn.click": [
      {
        "timestamp": "2025-10-07T00:00:37.282989",
        "status": "up",
        "latency": 0.897654,
        "is_best": false
      },
      {
        "timestamp": "2025-10-07T01:00:20.326689",
        "status": "up",
        "latency": 0.794538,
        "is_best": false
      },
      {
        "timestamp": "2025-10-07T02:00:20.228888",
        "status": "up",
        "latency": 0.787344,
        "is_best": false
      },
      {
        "timestamp": "2025-10-07T03:00:26.102001",
        "status": "up",
        "latency": 0.805863,
        "is_best": false
      },
      {
        "timestamp": "2025-10-07T04:00:35.656550",
        "status": "up",
        "latency": 0.901573,
        "is_best": false
      },
      {
        "timestamp": "2025-10-07T05:00:20.460522",
        "status": "up",
        "latency": 0.954598,
        "is_best": false
      },
      {
        "timestamp": "2025-10-07T06:00:20.402500",
        "status": "up",
        "latency": 0.917178,
        "is_best": false
      },
      {
        "timestamp": "2025-10-07T07:00:19.902679",
        "status": "up",
        "latency": 0.90039,
        "is_best": false
      },
      {
        "timestamp": "2025-10-07T08:00:20.228669",
        "status": "up",
        "latency": 0.938578,
        "is_best": false
      },
      {
        "timestamp": "2025-10-07T09:00:24.502149",
        "status": "up",
        "latency": 0.955918,
        "is_best": false
      },
      {
        "timestamp": "2025-10-07T10:00:19.972862",
        "status": "up",
        "latency": 0.779816,
        "is_best": false
      },
      {
        "timestamp": "2025-10-07T11:00:20.624846",
        "status": "up",
        "latency": 0.778641,
        "is_best": true
      },
      {
        "timestamp": "2025-10-07T12:00:22.571614",
        "status": "up",
        "latency": 0.791445,
        "is_best": false
      },
      {
        "timestamp": "2025-10-07T13:00:23.788412",
        "status": "up",
        "latency": 0.765983,
        "is_best": false
      },
      {
        "timestamp": "2025-10-07T14:00:23.823051",
        "status": "up",
        "latency": 0.963492,
        "is_best": false
      },
      {
        "timestamp": "2025-10-07T15:00:24.480258",
        "status": "up",
        "latency": 0.755087,
        "is_best": false
      },
      {
        "timestamp": "2025-10-07T16:00:26.349987",
        "status": "up",
        "latency": 0.970024,
        "is_best": false
      },
      {
        "timestamp": "2025-10-07T17:00:25.777166",
        "status": "up",
        "latency": 0.779237,
        "is_best": false
      },
      {
        "timestamp": "2025-10-07T18:00:29.650938",
        "status": "up",
        "latency": 0.781215,
        "is_best": false
      },
      {
        "timestamp": "2025-10-07T19:01:02.538674",
        "status": "up",
        "latency": 0.742846,
        "is_best": false
      },
      {
        "timestamp": "2025-10-07T20:00:34.005990",
        "status": "up",
        "latency": 0.767993,
        "is_best": true
      },
      {
        "timestamp": "2025-10-07T21:00:35.158508",
        "status": "up",
        "latency": 0.782719,
        "is_best": true
      },
      {
        "timestamp": "2025-10-07T22:00:35.422729",
        "status": "up",
        "latency": 0.866852,
        "is_best": false
      },
      {
        "timestamp": "2025-10-08T00:00:23.886730",
        "status": "up",
        "latency": 0.789215,
        "is_best": false
      }
    ],
    "https://erxiaofn.site": [
      {
        "timestamp": "2025-10-07T00:00:37.282989",
        "status": "up",
        "latency": 0.780739,
        "is_best": true
      },
      {
        "timestamp": "2025-10-07T01:00:20.326689",
        "status": "up",
        "latency": 0.772905,
        "is_best": false
      },
      {
        "timestamp": "2025-10-07T02:00:20.228888",
        "status": "up",
        "latency": 0.99789,
        "is_best": false
      },
      {
        "timestamp": "2025-10-07T03:00:26.102001",
        "status": "up",
        "latency": 0.806815,
        "is_best": false
      },
      {
        "timestamp": "2025-10-07T04:00:35.656550",
        "status": "up",
        "latency": 0.943989,
        "is_best": false
      },
      {
        "timestamp": "2025-10-07T05:00:20.460522",
        "status": "up",
        "latency": 0.972579,
        "is_best": false
      },
      {
        "timestamp": "2025-10-07T06:00:20.402500",
        "status": "up",
        "latency": 0.92881,
        "is_best": false
      },
      {
        "timestamp": "2025-10-07T07:00:19.902679",
        "status": "up",
        "latency": 0.773327,
        "is_best": false
      },
      {
        "timestamp": "2025-10-07T08:00:20.228669",
        "status": "up",
        "latency": 0.928489,
        "is_best": false
      },
      {
        "timestamp": "2025-10-07T09:00:24.502149",
        "status": "up",
        "latency": 0.947148,
        "is_best": false
      },
      {
        "timestamp": "2025-10-07T10:00:19.972862",
        "status": "up",
        "latency": 0.888721,
        "is_best": false
      },
      {
        "timestamp": "2025-10-07T11:00:20.624846",
        "status": "up",
        "latency": 0.924929,
        "is_best": false
      },
      {
        "timestamp": "2025-10-07T12:00:22.571614",
        "status": "up",
        "latency": 0.906804,
        "is_best": false
      },
      {
        "timestamp": "2025-10-07T13:00:23.788412",
        "status": "up",
        "latency": 0.76064,
        "is_best": true
      },
      {
        "timestamp": "2025-10-07T14:00:23.823051",
        "status": "up",
        "latency": 0.968015,
        "is_best": false
      },
      {
        "timestamp": "2025-10-07T15:00:24.480258",
        "status": "up",
        "latency": 0.781762,
        "is_best": false
      },
      {
        "timestamp": "2025-10-07T16:00:26.349987",
        "status": "up",
        "latency": 0.964322,
        "is_best": false
      },
      {
        "timestamp": "2025-10-07T17:00:25.777166",
        "status": "up",
        "latency": 0.809962,
        "is_best": false
      },
      {
        "timestamp": "2025-10-07T18:00:29.650938",
        "status": "up",
        "latency": 0.80209,
        "is_best": false
      },
      {
        "timestamp": "2025-10-07T19:01:02.538674",
        "status": "up",
        "latency": 0.814955,
        "is_best": false
      },
      {
        "timestamp": "2025-10-07T20:00:34.005990",
        "status": "up",
        "latency": 0.954428,
        "is_best": false
      },
      {
        "timestamp": "2025-10-07T21:00:35.158508",
        "status": "up",
        "latency": 0.800355,
        "is_best": false
      },
      {
        "timestamp": "2025-10-07T22:00:35.422729",
        "status": "up",
        "latency": 0.805107,
        "is_best": false
      },
      {
        "timestamp": "2025-10-08T00:00:23.886730",
        "status": "up",
        "latency": 0.824837,
        "is_best": false
      }
    ],
    "https://www.xhww.net": [
      {
        "timestamp": "2025-10-07T00:00:37.282989",
        "status": "up",
        "latency": 0.960958,
        "is_best": false
      },
      {
        "timestamp": "2025-10-07T01:00:20.326689",
        "status": "up",
        "latency": 0.904382,
        "is_best": false
      },
      {
        "timestamp": "2025-10-07T02:00:20.228888",
        "status": "up",
        "latency": 0.997263,
        "is_best": false
      },
      {
        "timestamp": "2025-10-07T03:00:26.102001",
        "status": "up",
        "latency": 0.947545,
        "is_best": false
      },
      {
        "timestamp": "2025-10-07T04:00:35.656550",
        "status": "up",
        "latency": 0.920965,
        "is_best": false
      },
      {
        "timestamp": "2025-10-07T05:00:20.460522",
        "status": "up",
        "latency": 0.985764,
        "is_best": false
      },
      {
        "timestamp": "2025-10-07T06:00:20.402500",
        "status": "up",
        "latency": 0.918312,
        "is_best": false
      },
      {
        "timestamp": "2025-10-07T07:00:19.902679",
        "status": "up",
        "latency": 0.971378,
        "is_best": false
      },
      {
        "timestamp": "2025-10-07T08:00:20.228669",
        "status": "up",
        "latency": 0.963098,
        "is_best": false
      },
      {
        "timestamp": "2025-10-07T09:00:24.502149",
        "status": "up",
        "latency": 0.946113,
        "is_best": false
      },
      {
        "timestamp": "2025-10-07T10:00:19.972862",
        "status": "up",
        "latency": 0.921969,
        "is_best": false
      },
      {
        "timestamp": "2025-10-07T11:00:20.624846",
        "status": "up",
        "latency": 1.988271,
        "is_best": false
      },
      {
        "timestamp": "2025-10-07T12:00:22.571614",
        "status": "up",
        "latency": 0.914299,
        "is_best": false
      },
      {
        "timestamp": "2025-10-07T13:00:23.788412",
        "status": "up",
        "latency": 0.933799,
        "is_best": false
      },
      {
        "timestamp": "2025-10-07T14:00:23.823051",
        "status": "up",
        "latency": 0.917803,
        "is_best": false
      },
      {
        "timestamp": "2025-10-07T15:00:24.480258",
        "status": "up",
        "latency": 0.915669,
        "is_best": false
      },
      {
        "timestamp": "2025-10-07T16:00:26.349987",
        "status": "up",
        "latency": 0.827924,
        "is_best": false
      },
      {
        "timestamp": "2025-10-07T17:00:25.777166",
        "status": "up",
        "latency": 0.953865,
        "is_best": false
      },
      {
        "timestamp": "2025-10-07T18:00:29.650938",
        "status": "up",
        "latency": 1.683473,
        "is_best": false
      },
      {
        "timestamp": "2025-10-07T19:01:02.538674",
        "status": "up",
        "latency": 0.918291,
        "is_best": false
      },
      {
        "timestamp": "2025-10-07T20:00:34.005990",
        "status": "up",
        "latency": 0.913789,
        "is_best": false
      },
      {
        "timestamp": "2025-10-07T21:00:35.158508",
        "status": "up",
        "latency": 2.323973,
        "is_best": false
      },
      {
        "timestamp": "2025-10-07T22:00:35.422729",
        "status": "up",
        "latency": 1.125337,
        "is_best": false
      },
      {
        "timestamp": "2025-10-08T00:00:23.886730",
        "status": "up",
        "latency": 2.047772,
        "is_best": false
      }
    ]
  },
  "虎斑": {
    "http://103.45.162.207:20720": [
      {
        "timestamp": "2025-10-07T00:00:37.282989",
        "status": "up",
        "latency": 0.132189,
        "is_best": true
      },
      {
        "timestamp": "2025-10-07T01:00:20.326689",
        "status": "up",
        "latency": 0.117357,
        "is_best": true
      },
      {
        "timestamp": "2025-10-07T02:00:20.228888",
        "status": "up",
        "latency": 0.859138,
        "is_best": true
      },
      {
        "timestamp": "2025-10-07T03:00:26.102001",
        "status": "up",
        "latency": 0.858766,
        "is_best": true
      },
      {
        "timestamp": "2025-10-07T04:00:35.656550",
        "status": "up",
        "latency": 0.843611,
        "is_best": true
      },
      {
        "timestamp": "2025-10-07T05:00:20.460522",
        "status": "up",
        "latency": 0.843225,
        "is_best": true
      },
      {
        "timestamp": "2025-10-07T06:00:20.402500",
        "status": "up",
        "latency": 0.105686,
        "is_best": true
      },
      {
        "timestamp": "2025-10-07T07:00:19.902679",
        "status": "up",
        "latency": 0.865067,
        "is_best": true
      },
      {
        "timestamp": "2025-10-07T08:00:20.228669",
        "status": "up",
        "latency": 0.842903,
        "is_best": true
      },
      {
        "timestamp": "2025-10-07T09:00:24.502149",
        "status": "up",
        "latency": 0.858863,
        "is_best": true
      },
      {
        "timestamp": "2025-10-07T10:00:19.972862",
        "status": "up",
        "latency": 0.13848,
        "is_best": true
      },
      {
        "timestamp": "2025-10-07T11:00:20.624846",
        "status": "up",
        "latency": 0.109801,
        "is_best": true
      },
      {
        "timestamp": "2025-10-07T12:00:22.571614",
        "status": "up",
        "latency": 0.134366,
        "is_best": true
      },
      {
        "timestamp": "2025-10-07T13:00:23.788412",
        "status": "up",
        "latency": 0.114456,
        "is_best": true
      },
      {
        "timestamp": "2025-10-07T14:00:23.823051",
        "status": "up",
        "latency": 0.133746,
        "is_best": true
      },
      {
        "timestamp": "2025-10-07T15:00:24.480258",
        "status": "up",
        "latency": 0.119049,
        "is_best": true
      },
      {
        "timestamp": "2025-10-07T16:00:26.349987",
        "status": "up",
        "latency": 0.11211,
        "is_best": true
      },
      {
        "timestamp": "2025-10-07T17:00:25.777166",
        "status": "up",
        "latency": 0.119213,
        "is_best": true
      },
      {
        "timestamp": "2025-10-07T18:00:29.650938",
        "status": "up",
        "latency": 0.115496,
        "is_best": true
      },
      {
        "timestamp": "2025-10-07T19:01:02.538674",
        "status": "up",
        "latency": 0.120982,
        "is_best": true
      },
      {
        "timestamp": "2025-10-07T20:00:34.005990",
        "status": "up",
        "latency": 0.270361,
        "is_best": true
      },
      {
        "timestamp": "2025-10-07T21:00:35.158508",
        "status": "up",
        "latency": 0.128237,
        "is_best": true
      },
      {
        "timestamp": "2025-10-07T22:00:35.422729",
        "status": "up",
        "latency": 0.154811,
        "is_best": true
      },
      {
        "timestamp": "2025-10-08T00:00:23.886730",
        "status": "up",
        "latency": 0.12124,
        "is_best": true
      }
    ]
  },
  "闪电": {
    "http://1.95.79.193": [
      {
        "timestamp": "2025-10-07T00:00:37.282989",
        "status": "down",
        "latency": null,
        "is_best": false,
        "error_detail": "连接失败"
      },
      {
        "timestamp": "2025-10-07T01:00:20.326689",
        "status": "down",
        "latency": null,
        "is_best": false,
        "error_detail": "连接失败"
      },
      {
        "timestamp": "2025-10-07T02:00:20.228888",
        "status": "down",
        "latency": null,
        "is_best": false,
        "error_detail": "连接失败"
      },
      {
        "timestamp": "2025-10-07T03:00:26.102001",
        "status": "down",
        "latency": null,
        "is_best": false,
        "error_detail": "连接失败"
      },
      {
        "timestamp": "2025-10-07T04:00:35.656550",
        "status": "down",
        "latency": null,
        "is_best": false,
        "error_detail": "连接失败"
      },
      {
        "timestamp": "2025-10-07T05:00:20.460522",
        "status": "down",
        "latency": null,
        "is_best": false,
        "error_detail": "连接失败"
      },
      {
        "timestamp": "2025-10-07T06:00:20.402500",
        "status": "down",
        "latency": null,
        "is_best": false,
        "error_detail": "连接失败"
      },
      {
        "timestamp": "2025-10-07T07:00:19.902679",
        "status": "down",
        "latency": null,
        "is_best": false,
        "error_detail": "连接失败"
      },
      {
        "timestamp": "2025-10-07T08:00:20.228669",
        "status": "down",
        "latency": null,
        "is_best": false,
        "error_detail": "连接失败"
      },
      {
        "timestamp": "2025-10-07T09:00:24.502149",
        "status": "down",
        "latency": null,
        "is_best": false,
        "error_detail": "连接失败"
      },
      {
        "timestamp": "2025-10-07T10:00:19.972862",
        "status": "down",
        "latency": null,
        "is_best": false,
        "error_detail": "连接失败"
      },
      {
        "timestamp": "2025-10-07T11:00:20.624846",
        "status": "down",
        "latency": null,
        "is_best": false,
        "error_detail": "连接失败"
      },
      {
        "timestamp": "2025-10-07T12:00:22.571614",
        "status": "down",
        "latency": null,
        "is_best": false,
        "error_detail": "连接失败"
      },
      {
        "timestamp": "2025-10-07T13:00:23.788412",
        "status": "down",
        "latency": null,
        "is_best": false,
        "error_detail": "连接失败"
      },
      {
        "timestamp": "2025-10-07T14:00:23.823051",
        "status": "down",
        "latency": null,
        "is_best": false,
        "error_detail": "连接失败"
      },
      {
        "timestamp": "2025-10-07T15:00:24.480258",
        "status": "down",
        "latency": null,
        "is_best": false,
        "error_detail": "连接失败"
      },
      {
        "timestamp": "2025-10-07T16:00:26.349987",
        "status": "down",
        "latency": null,
        "is_best": false,
        "error_detail": "连接失败"
      },
      {
        "timestamp": "2025-10-07T17:00:25.777166",
        "status": "down",
        "latency": null,
        "is_best": false,
        "error_detail": "连接失败"
      },
      {
        "timestamp": "2025-10-07T18:00:29.650938",
        "status": "down",
        "latency": null,
        "is_best": false,
        "error_detail": "连接失败"
      },
      {
        "timestamp": "2025-10-07T19:01:02.538674",
        "status": "down",
        "latency": null,
        "is_best": false,
        "error_detail": "连接失败"
      },
      {
        "timestamp": "2025-10-07T20:00:34.005990",
        "status": "down",
        "latency": null,
        "is_best": false,
        "error_detail": "连接失败"
      },
      {
        "timestamp": "2025-10-07T21:00:35.158508",
        "status": "down",
        "latency": null,
        "is_best": false,
        "error_detail": "连接失败"
      },
      {
        "timestamp": "2025-10-07T22:00:35.422729",
        "status": "down",
        "latency": null,
        "is_best": false,
        "error_detail": "连接失败"
      },
      {
        "timestamp": "2025-10-08T00:00:23.886730",
        "status": "down",
        "latency": null,
        "is_best": false,
        "error_detail": "连接失败"
      }
    ]
  },
  "小斑": {
    "http://xsayang.fun:12512": [
      {
        "timestamp": "2025-10-07T00:00:37.282989",
        "status": "up",
        "latency": 0.244398,
        "is_best": true
      },
      {
        "timestamp": "2025-10-07T01:00:20.326689",
        "status": "up",
        "latency": 0.225553,
        "is_best": true
      },
      {
        "timestamp": "2025-10-07T02:00:20.228888",
        "status": "up",
        "latency": 0.565499,
        "is_best": true
      },
      {
        "timestamp": "2025-10-07T03:00:26.102001",
        "status": "down",
        "latency": null,
        "is_best": false,
        "error_detail": "连接失败"
      },
      {
        "timestamp": "2025-10-07T04:00:35.656550",
        "status": "up",
        "latency": 0.558029,
        "is_best": true
      },
      {
        "timestamp": "2025-10-07T05:00:20.460522",
        "status": "up",
        "latency": 0.218193,
        "is_best": true
      },
      {
        "timestamp": "2025-10-07T06:00:20.402500",
        "status": "up",
        "latency": 0.242029,
        "is_best": true
      },
      {
        "timestamp": "2025-10-07T07:00:19.902679",
        "status": "up",
        "latency": 0.219387,
        "is_best": true
      },
      {
        "timestamp": "2025-10-07T08:00:20.228669",
        "status": "up",
        "latency": 0.23475,
        "is_best": true
      },
      {
        "timestamp": "2025-10-07T09:00:24.502149",
        "status": "up",
        "latency": 0.244889,
        "is_best": true
      },
      {
        "timestamp": "2025-10-07T10:00:19.972862",
        "status": "up",
        "latency": 0.246815,
        "is_best": true
      },
      {
        "timestamp": "2025-10-07T11:00:20.624846",
        "status": "up",
        "latency": 0.240325,
        "is_best": true
      },
      {
        "timestamp": "2025-10-07T12:00:22.571614",
        "status": "up",
        "latency": 0.25498,
        "is_best": true
      },
      {
        "timestamp": "2025-10-07T13:00:23.788412",
        "status": "up",
        "latency": 0.238926,
        "is_best": true
      },
      {
        "timestamp": "2025-10-07T14:00:23.823051",
        "status": "up",
        "latency": 0.224145,
        "is_best": true
      },
      {
        "timestamp": "2025-10-07T15:00:24.480258",
        "status": "up",
        "latency": 0.225216,
        "is_best": true
      },
      {
        "timestamp": "2025-10-07T16:00:26.349987",
        "status": "up",
        "latency": 0.234114,
        "is_best": true
      },
      {
        "timestamp": "2025-10-07T17:00:25.777166",
        "status": "up",
        "latency": 0.236274,
        "is_best": true
      },
      {
        "timestamp": "2025-10-07T18:00:29.650938",
        "status": "up",
        "latency": 0.261098,
        "is_best": true
      },
      {
        "timestamp": "2025-10-07T19:01:02.538674",
        "status": "up",
        "latency": 0.244305,
        "is_best": true
      },
      {
        "timestamp": "2025-10-07T20:00:34.005990",
        "status": "up",
        "latency": 0.431367,
        "is_best": true
      },
      {
        "timestamp": "2025-10-07T21:00:35.158508",
        "status": "up",
        "latency": 0.287947,
        "is_best": true
      },
      {
        "timestamp": "2025-10-07T22:00:35.422729",
        "status": "up",
        "latency": 0.244258,
        "is_best": true
      },
      {
        "timestamp": "2025-10-08T00:00:23.886730",
        "status": "up",
        "latency": 0.249716,
        "is_best": true
      }
    ]
  }
}